{
  "description": "T2_balanced w/ regime-tilted top-3 weights (1.5x favored / 0.75x other)",
  "n_monthly": 189,
  "stats": {
    "cagr": 0.19540751010647872,
    "sharpe": 1.2264021551837092,
    "max_dd": -0.20244268206873106,
    "n": 189
  },
  "monthly_returns": [
    {
      "date": "2010-07-27",
      "fwd_ret": 0.044408251537091256
    },
    {
      "date": "2010-08-31",
      "fwd_ret": 0.03383658732481076
    },
    {
      "date": "2010-09-29",
      "fwd_ret": 0.0592719995456095
    },
    {
      "date": "2010-10-25",
      "fwd_ret": 0.026056865039511407
    },
    {
      "date": "2010-11-30",
      "fwd_ret": 0.02740923788264097
    },
    {
      "date": "2010-12-29",
      "fwd_ret": 0.060739026056355984
    },
    {
      "date": "2011-01-25",
      "fwd_ret": 0.052684655162545835
    },
    {
      "date": "2011-02-23",
      "fwd_ret": 0.012407427072667676
    },
    {
      "date": "2011-03-30",
      "fwd_ret": 0.004842548179037582
    },
    {
      "date": "2011-04-26",
      "fwd_ret": -0.008812075781067616
    },
    {
      "date": "2011-05-24",
      "fwd_ret": -0.019741591202011563
    },
    {
      "date": "2011-06-29",
      "fwd_ret": 0.03158271523026662
    },
    {
      "date": "2011-07-26",
      "fwd_ret": 0.03556492380028372
    },
    {
      "date": "2011-08-30",
      "fwd_ret": -0.03171572909787595
    },
    {
      "date": "2011-09-28",
      "fwd_ret": 0.03382142713830205
    },
    {
      "date": "2011-10-31",
      "fwd_ret": 0.011394736145745363
    },
    {
      "date": "2011-11-29",
      "fwd_ret": -0.012313331743474097
    },
    {
      "date": "2011-12-28",
      "fwd_ret": 0.03331016968094738
    },
    {
      "date": "2012-01-25",
      "fwd_ret": 0.045608131387691556
    },
    {
      "date": "2012-02-23",
      "fwd_ret": 0.061134172108572374
    },
    {
      "date": "2012-03-29",
      "fwd_ret": -0.010697395931432466
    },
    {
      "date": "2012-04-25",
      "fwd_ret": -0.07398287229850732
    },
    {
      "date": "2012-05-31",
      "fwd_ret": 0.026330683573405893
    },
    {
      "date": "2012-06-28",
      "fwd_ret": 0.007037370653310254
    },
    {
      "date": "2012-07-25",
      "fwd_ret": 0.02959520726146741
    },
    {
      "date": "2012-08-29",
      "fwd_ret": 0.03508037540974543
    },
    {
      "date": "2012-09-27",
      "fwd_ret": -0.032255374563987194
    },
    {
      "date": "2012-10-24",
      "fwd_ret": -0.006133442582492404
    },
    {
      "date": "2012-11-26",
      "fwd_ret": -0.02711738614466504
    },
    {
      "date": "2012-12-24",
      "fwd_ret": 0.03326925916026178
    },
    {
      "date": "2013-01-25",
      "fwd_ret": 0.018753942650180933
    },
    {
      "date": "2013-02-25",
      "fwd_ret": 0.035806620782955136
    },
    {
      "date": "2013-03-25",
      "fwd_ret": 0.00626975873983524
    },
    {
      "date": "2013-04-24",
      "fwd_ret": 0.04779520164494011
    },
    {
      "date": "2013-05-30",
      "fwd_ret": -0.008087345458114958
    },
    {
      "date": "2013-06-27",
      "fwd_ret": 0.02886606915215765
    },
    {
      "date": "2013-07-25",
      "fwd_ret": -0.006544345232036583
    },
    {
      "date": "2013-08-29",
      "fwd_ret": 0.050359175276954805
    },
    {
      "date": "2013-09-27",
      "fwd_ret": 0.01532603587103325
    },
    {
      "date": "2013-10-31",
      "fwd_ret": 0.031219508748494364
    },
    {
      "date": "2013-11-29",
      "fwd_ret": 0.028940564022968147
    },
    {
      "date": "2013-12-30",
      "fwd_ret": -0.021007634107611212
    },
    {
      "date": "2014-01-27",
      "fwd_ret": 0.07010096061042688
    },
    {
      "date": "2014-02-25",
      "fwd_ret": -0.0027854711321271264
    },
    {
      "date": "2014-03-25",
      "fwd_ret": -0.01006714828454739
    },
    {
      "date": "2014-04-25",
      "fwd_ret": 0.03797188000324832
    },
    {
      "date": "2014-05-23",
      "fwd_ret": 0.05292903536068932
    },
    {
      "date": "2014-06-30",
      "fwd_ret": -0.03225879149697804
    },
    {
      "date": "2014-07-25",
      "fwd_ret": 0.023689680290938986
    },
    {
      "date": "2014-08-29",
      "fwd_ret": -0.03001849648603533
    },
    {
      "date": "2014-09-29",
      "fwd_ret": 0.005923977403876586
    },
    {
      "date": "2014-10-31",
      "fwd_ret": 0.036366874762896684
    },
    {
      "date": "2014-11-21",
      "fwd_ret": 0.003024480401239149
    },
    {
      "date": "2014-12-30",
      "fwd_ret": -0.026270223918632724
    },
    {
      "date": "2015-01-27",
      "fwd_ret": 0.07878864305650708
    },
    {
      "date": "2015-02-25",
      "fwd_ret": -0.03032484092703608
    },
    {
      "date": "2015-03-25",
      "fwd_ret": 0.036770945960279924
    },
    {
      "date": "2015-04-27",
      "fwd_ret": 0.007739371870251521
    },
    {
      "date": "2015-05-26",
      "fwd_ret": -0.0050840679168079874
    },
    {
      "date": "2015-06-30",
      "fwd_ret": 0.026614000756951795
    },
    {
      "date": "2015-07-27",
      "fwd_ret": -0.06244619892518023
    },
    {
      "date": "2015-08-31",
      "fwd_ret": 0.0023048436050290277
    },
    {
      "date": "2015-09-29",
      "fwd_ret": 0.0261577837749494
    },
    {
      "date": "2015-10-26",
      "fwd_ret": -0.0041561082838509796
    },
    {
      "date": "2015-11-23",
      "fwd_ret": 0.00482528396779001
    },
    {
      "date": "2015-12-30",
      "fwd_ret": -0.09114601056786809
    },
    {
      "date": "2016-01-26",
      "fwd_ret": 0.02322695336837182
    },
    {
      "date": "2016-02-24",
      "fwd_ret": 0.00220485621332559
    },
    {
      "date": "2016-03-31",
      "fwd_ret": 0.047193506681768777
    },
    {
      "date": "2016-04-25",
      "fwd_ret": -0.0002992834498439234
    },
    {
      "date": "2016-05-31",
      "fwd_ret": 0.013039643309253723
    },
    {
      "date": "2016-06-28",
      "fwd_ret": 0.016993885939008923
    },
    {
      "date": "2016-07-26",
      "fwd_ret": 0.018888288955876992
    },
    {
      "date": "2016-08-30",
      "fwd_ret": 0.030982495598923854
    },
    {
      "date": "2016-09-28",
      "fwd_ret": -0.0038499952509164306
    },
    {
      "date": "2016-10-31",
      "fwd_ret": 0.06103850866086967
    },
    {
      "date": "2016-11-29",
      "fwd_ret": 0.025318819853536012
    },
    {
      "date": "2016-12-28",
      "fwd_ret": 0.016943324046988707
    },
    {
      "date": "2017-01-25",
      "fwd_ret": 0.02365310683254331
    },
    {
      "date": "2017-02-23",
      "fwd_ret": 0.025093045054259872
    },
    {
      "date": "2017-03-30",
      "fwd_ret": 0.03202797351428224
    },
    {
      "date": "2017-04-25",
      "fwd_ret": 0.06975533683263513
    },
    {
      "date": "2017-05-31",
      "fwd_ret": -0.026307462687734928
    },
    {
      "date": "2017-06-28",
      "fwd_ret": 0.039962831014446566
    },
    {
      "date": "2017-07-25",
      "fwd_ret": -0.014339003661755648
    },
    {
      "date": "2017-08-29",
      "fwd_ret": -0.010210763891693153
    },
    {
      "date": "2017-09-27",
      "fwd_ret": 0.020412378392443187
    },
    {
      "date": "2017-10-31",
      "fwd_ret": -0.003017822648171002
    },
    {
      "date": "2017-11-29",
      "fwd_ret": 0.013836672756829574
    },
    {
      "date": "2017-12-28",
      "fwd_ret": 0.07646150306202615
    },
    {
      "date": "2018-01-25",
      "fwd_ret": -0.07506461665677364
    },
    {
      "date": "2018-02-23",
      "fwd_ret": -0.059110183651710016
    },
    {
      "date": "2018-03-23",
      "fwd_ret": -0.03952837921320358
    },
    {
      "date": "2018-04-24",
      "fwd_ret": 0.052177181547680515
    },
    {
      "date": "2018-05-30",
      "fwd_ret": 0.0019438629026785836
    },
    {
      "date": "2018-06-27",
      "fwd_ret": 0.022031125318419286
    },
    {
      "date": "2018-07-25",
      "fwd_ret": 0.014451475416397389
    },
    {
      "date": "2018-08-29",
      "fwd_ret": 0.009045347182593977
    },
    {
      "date": "2018-09-27",
      "fwd_ret": -0.13246895789143442
    },
    {
      "date": "2018-10-31",
      "fwd_ret": -0.002750496829930074
    },
    {
      "date": "2018-11-29",
      "fwd_ret": 0.010267372783688167
    },
    {
      "date": "2018-12-31",
      "fwd_ret": 0.030685800605152053
    },
    {
      "date": "2019-01-25",
      "fwd_ret": 0.027037315191050182
    },
    {
      "date": "2019-02-25",
      "fwd_ret": 0.0038542413142402436
    },
    {
      "date": "2019-03-25",
      "fwd_ret": 0.09718020702191339
    },
    {
      "date": "2019-04-25",
      "fwd_ret": -0.12841492837205842
    },
    {
      "date": "2019-05-31",
      "fwd_ret": 0.12741985718606497
    },
    {
      "date": "2019-06-28",
      "fwd_ret": 0.021722654868013613
    },
    {
      "date": "2019-07-25",
      "fwd_ret": 0.02468642250480253
    },
    {
      "date": "2019-08-29",
      "fwd_ret": -0.010434851504367314
    },
    {
      "date": "2019-09-27",
      "fwd_ret": 0.048032892641161645
    },
    {
      "date": "2019-10-31",
      "fwd_ret": -0.004234909229941261
    },
    {
      "date": "2019-11-29",
      "fwd_ret": 0.10458862542791265
    },
    {
      "date": "2019-12-30",
      "fwd_ret": -0.008340852004727709
    },
    {
      "date": "2020-01-27",
      "fwd_ret": -0.10516933771500048
    },
    {
      "date": "2020-02-25",
      "fwd_ret": -0.030943401858902417
    },
    {
      "date": "2020-03-31",
      "fwd_ret": 0.030767502999528774
    },
    {
      "date": "2020-04-27",
      "fwd_ret": 0.010417615838655948
    },
    {
      "date": "2020-05-26",
      "fwd_ret": 0.07292412634468126
    },
    {
      "date": "2020-06-30",
      "fwd_ret": -0.0032572340802195336
    },
    {
      "date": "2020-07-27",
      "fwd_ret": 0.12252748379689363
    },
    {
      "date": "2020-08-31",
      "fwd_ret": -0.06055666551888431
    },
    {
      "date": "2020-09-29",
      "fwd_ret": 0.0065573685628218335
    },
    {
      "date": "2020-10-26",
      "fwd_ret": 0.04936920283790065
    },
    {
      "date": "2020-11-23",
      "fwd_ret": 0.06619319076266317
    },
    {
      "date": "2020-12-30",
      "fwd_ret": 0.05822924986029694
    },
    {
      "date": "2021-01-26",
      "fwd_ret": 0.1406629283711834
    },
    {
      "date": "2021-02-24",
      "fwd_ret": 0.02072879231971053
    },
    {
      "date": "2021-03-31",
      "fwd_ret": 0.0034788151817621857
    },
    {
      "date": "2021-04-26",
      "fwd_ret": 0.03882579374766063
    },
    {
      "date": "2021-05-24",
      "fwd_ret": 0.05275728925741496
    },
    {
      "date": "2021-06-29",
      "fwd_ret": 0.032844737342577826
    },
    {
      "date": "2021-07-27",
      "fwd_ret": 0.028688941758111097
    },
    {
      "date": "2021-08-31",
      "fwd_ret": -0.04567920544258404
    },
    {
      "date": "2021-09-29",
      "fwd_ret": 0.08127205075179289
    },
    {
      "date": "2021-10-25",
      "fwd_ret": 0.011955233107231011
    },
    {
      "date": "2021-11-30",
      "fwd_ret": 0.040293243726135256
    },
    {
      "date": "2021-12-29",
      "fwd_ret": -0.10840918123350593
    },
    {
      "date": "2022-01-25",
      "fwd_ret": 0.047755609943398336
    },
    {
      "date": "2022-02-23",
      "fwd_ret": 0.13393583703197973
    },
    {
      "date": "2022-03-30",
      "fwd_ret": -0.009100245276439189
    },
    {
      "date": "2022-04-26",
      "fwd_ret": 0.10976043760378336
    },
    {
      "date": "2022-05-24",
      "fwd_ret": -0.036296573733192
    },
    {
      "date": "2022-06-30",
      "fwd_ret": 0.004595623308865937
    },
    {
      "date": "2022-07-26",
      "fwd_ret": 0.03311075985345675
    },
    {
      "date": "2022-08-30",
      "fwd_ret": -0.04852530241893671
    },
    {
      "date": "2022-09-28",
      "fwd_ret": 0.016635419114775826
    },
    {
      "date": "2022-10-31",
      "fwd_ret": 0.0247530783705616
    },
    {
      "date": "2022-11-29",
      "fwd_ret": -0.015363709954701033
    },
    {
      "date": "2022-12-28",
      "fwd_ret": 0.06000997554083205
    },
    {
      "date": "2023-01-25",
      "fwd_ret": -0.013336660864338124
    },
    {
      "date": "2023-02-23",
      "fwd_ret": 0.05387771396057721
    },
    {
      "date": "2023-03-30",
      "fwd_ret": -0.05645425426560015
    },
    {
      "date": "2023-04-25",
      "fwd_ret": 0.09424691639157892
    },
    {
      "date": "2023-05-31",
      "fwd_ret": 0.05018395980164567
    },
    {
      "date": "2023-06-29",
      "fwd_ret": 0.03927901929729345
    },
    {
      "date": "2023-07-25",
      "fwd_ret": -0.05278972084216728
    },
    {
      "date": "2023-08-29",
      "fwd_ret": 0.0009510055344191075
    },
    {
      "date": "2023-09-27",
      "fwd_ret": -0.03380487711257498
    },
    {
      "date": "2023-10-31",
      "fwd_ret": 0.03361479527622744
    },
    {
      "date": "2023-11-29",
      "fwd_ret": 0.008254503819904918
    },
    {
      "date": "2023-12-28",
      "fwd_ret": 0.02207307272371376
    },
    {
      "date": "2024-01-25",
      "fwd_ret": 0.059365712801201925
    },
    {
      "date": "2024-02-23",
      "fwd_ret": 0.03436442727934821
    },
    {
      "date": "2024-03-22",
      "fwd_ret": -0.04918988208889635
    },
    {
      "date": "2024-04-24",
      "fwd_ret": -0.01577105673543796
    },
    {
      "date": "2024-05-30",
      "fwd_ret": 0.024640702122377702
    },
    {
      "date": "2024-06-28",
      "fwd_ret": -0.025926312221202494
    },
    {
      "date": "2024-07-25",
      "fwd_ret": 0.015233354407308858
    },
    {
      "date": "2024-08-29",
      "fwd_ret": 0.04713131426306735
    },
    {
      "date": "2024-09-27",
      "fwd_ret": 0.041456338699155305
    },
    {
      "date": "2024-10-31",
      "fwd_ret": 0.0025603132655754313
    },
    {
      "date": "2024-11-29",
      "fwd_ret": -0.03450648583562811
    },
    {
      "date": "2024-12-30",
      "fwd_ret": 0.01428482013562939
    },
    {
      "date": "2025-01-28",
      "fwd_ret": -0.048513890279995586
    },
    {
      "date": "2025-02-26",
      "fwd_ret": 0.0455234968310632
    },
    {
      "date": "2025-03-26",
      "fwd_ret": 0.05836588525151863
    },
    {
      "date": "2025-04-25",
      "fwd_ret": -0.007434838074792671
    },
    {
      "date": "2025-05-23",
      "fwd_ret": 0.01138582804751729
    },
    {
      "date": "2025-06-24",
      "fwd_ret": 0.041926156547435214
    },
    {
      "date": "2025-07-25",
      "fwd_ret": 0.015407989976064379
    },
    {
      "date": "2025-08-29",
      "fwd_ret": 0.1251123996059615
    },
    {
      "date": "2025-09-29",
      "fwd_ret": 0.042818266702898566
    },
    {
      "date": "2025-10-31",
      "fwd_ret": 0.008786444496287182
    },
    {
      "date": "2025-11-21",
      "fwd_ret": 0.07650795835816004
    },
    {
      "date": "2025-12-30",
      "fwd_ret": 0.1275268541379324
    },
    {
      "date": "2026-01-27",
      "fwd_ret": 0.0011976702456123096
    },
    {
      "date": "2026-02-25",
      "fwd_ret": -0.06807468232413202
    },
    {
      "date": "2026-03-04",
      "fwd_ret": 0.03425632110638656
    }
  ],
  "regime_accuracy": 0.6649572649572651
}